[
    {
        "model": "products.author",
        "pk": 1,
        "fields": {
            "name": "Harper Lee",
            "bio": "Author of To Kill a Mockingbird."
        }
    },
    {
        "model": "products.author",
        "pk": 2,
        "fields": {
            "name": "George Orwell",
            "bio": "Author of 1984."
        }
    },
    {
        "model": "products.author",
        "pk": 3,
        "fields": {
            "name": "Richard Dawkins",
            "bio": "Author of The Selfish Gene."
        }
    },
    {
        "model": "products.author",
        "pk": 4,
        "fields": {
            "name": "Yuval Noah Harari",
            "bio": "Author of Sapiens: A Brief History of Humankind."
        }
    }
]